timbr/__init__.py
timbr/exception.py
timbr/serializer.py
timbr/datastore/__init__.py
timbr/datastore/snapshot.py
timbr/legacy/__init__.py
timbr/legacy/serializer.py
timbr/machine/__init__.py
timbr/machine/base_machine.py
timbr/machine/dashboard.py
timbr/machine/display.py
timbr/machine/exception.py
timbr/machine/machine.py
timbr/machine/profiler.py
timbr/machine/util.py
timbr/notebook/__init__.py
timbr/util/__init__.py
timbr/util/cli.py
timbr/util/general.py
timbr-0.0.2.data/data/share/jupyter/nbextensions/timbr/timbr.js
timbr-0.0.2.data/data/share/jupyter/nbextensions/timbr_machine/machine.js
timbr-0.0.2.dist-info/DESCRIPTION.rst
timbr-0.0.2.dist-info/METADATA
timbr-0.0.2.dist-info/RECORD
timbr-0.0.2.dist-info/WHEEL
timbr-0.0.2.dist-info/entry_points.txt
timbr-0.0.2.dist-info/metadata.json
timbr-0.0.2.dist-info/top_level.txt
