Metadata-Version: 2.0
Name: timbr
Version: 0.0.2
Summary: Dask-based data collection and processing machines, snapshot datastores, and a jupyter notebook extension
Home-page: https://github.com/timbr-io/timbr-python
Author: Pramukta Kumar
Author-email: pramukta.kumar@timbr.io
License: MIT
Platform: UNKNOWN
Requires-Dist: argh (>=0.26.1)
Requires-Dist: dask
Requires-Dist: decorator (>=4.0.6)
Requires-Dist: ipython
Requires-Dist: jsonpath-rw (>=1.4.0)
Requires-Dist: jupyter-react
Requires-Dist: msgpack-python (>=0.4.6)
Requires-Dist: numpy
Requires-Dist: observed
Requires-Dist: pymongo (>=2.8)
Requires-Dist: simplejson (>=3.6.5)
Requires-Dist: tables (>=3.2.1)
